Metadata-Version: 1.0
Name: Sudoko-package-GKG
Version: 0.1
Summary: Sudoko Solver Package
Home-page: UNKNOWN
Author: UNKNOWN
Author-email: UNKNOWN
License: UNKNOWN
Platform: UNKNOWN
